quick_publish/__init__.py
quick_publish/changelog.py
quick_publish/cli.py
quick_publish/core.py
quick_publish/exceptions.py
quick_publish/git.py
quick_publish/version.py
quick_publish-0.1.7.dist-info/METADATA
quick_publish-0.1.7.dist-info/WHEEL
quick_publish-0.1.7.dist-info/entry_points.txt
quick_publish-0.1.7.dist-info/licenses/LICENSE
quick_publish-0.1.7.dist-info/RECORD
