Metadata-Version: 2.4
Name: quick-publish
Version: 0.1.7
Summary: Shipped a standard `npm publish` workflow with one click for Python packages
Project-URL: Homepage, https://github.com/quick-publish/quick-publish-py
Project-URL: Repository, https://github.com/quick-publish/quick-publish-py
Project-URL: Issues, https://github.com/quick-publish/quick-publish-py/issues
Author: quick-publish contributors
License: MIT License
License-File: LICENSE
Keywords: changelog,packaging,publish,release,semver
Classifier: Development Status :: 4 - Beta
Classifier: Intended Audience :: Developers
Classifier: License :: OSI Approved :: MIT License
Classifier: Operating System :: OS Independent
Classifier: Programming Language :: Python :: 3
Classifier: Programming Language :: Python :: 3.9
Classifier: Programming Language :: Python :: 3.10
Classifier: Programming Language :: Python :: 3.11
Classifier: Programming Language :: Python :: 3.12
Classifier: Topic :: Software Development :: Build Tools
Classifier: Topic :: Software Development :: Libraries :: Python Modules
Requires-Python: >=3.9
Requires-Dist: click>=8.0.0
Requires-Dist: gitpython>=3.1.0
Requires-Dist: packaging>=21.0
Requires-Dist: questionary>=1.10.0
Requires-Dist: rich>=12.0.0
Requires-Dist: toml>=0.10.2
